flask_ask_sdk/__init__.py
flask_ask_sdk/__version__.py
flask_ask_sdk/skill_adapter.py
flask_ask_sdk-1.0.0.dist-info/METADATA
flask_ask_sdk-1.0.0.dist-info/RECORD
flask_ask_sdk-1.0.0.dist-info/WHEEL
flask_ask_sdk-1.0.0.dist-info/top_level.txt
